xvec/__init__.py
xvec/accessor.py
xvec/index.py
xvec/plotting.py
xvec/utils.py
xvec/zonal.py
xvec/tests/__init__.py
xvec/tests/conftest.py
xvec/tests/test_accessor.py
xvec/tests/test_index.py
xvec/tests/test_plotting.py
xvec/tests/test_xproj_integration.py
xvec/tests/test_zonal_stats.py
xvec/tests/baseline_images/test_plotting/1d.png
xvec/tests/baseline_images/test_plotting/categorical.png
xvec/tests/baseline_images/test_plotting/col.png
xvec/tests/baseline_images/test_plotting/col_row.png
xvec/tests/baseline_images/test_plotting/colwrap.png
xvec/tests/baseline_images/test_plotting/geom_switching.png
xvec/tests/baseline_images/test_plotting/hue.png
xvec/tests/baseline_images/test_plotting/single_custom_geometry.png
xvec/tests/baseline_images/test_plotting/unnamed.png
xvec/tests/baseline_images/test_plotting/var_geom.png
xvec/tests/baseline_images/test_plotting/var_geom_ds.png
xvec/tests/baseline_images/test_plotting/var_geom_facet.png
xvec/tests/baseline_images/test_plotting/void_dimension.png
xvec-0.5.1.dist-info/licenses/LICENSE
xvec-0.5.1.dist-info/METADATA
xvec-0.5.1.dist-info/WHEEL
xvec-0.5.1.dist-info/top_level.txt
xvec-0.5.1.dist-info/RECORD
