Metadata-Version: 2.4
Name: xvec
Version: 0.5.1
Summary: Vector data cubes for Xarray
Author-email: Martin Fleischmann <martin@martinfleischmann.net>, Benoît Bovy <benbovy@gmail.com>
Maintainer: Xvec contributors
License: MIT
Project-URL: Home, https://xvec.readthedocs.io
Project-URL: Repository, https://github.com/xarray-contrib/xvec
Keywords: GIS,cartography,pandas,shapely
Classifier: Intended Audience :: Science/Research
Classifier: License :: OSI Approved :: MIT License
Classifier: Operating System :: OS Independent
Classifier: Programming Language :: Python :: 3
Classifier: Topic :: Scientific/Engineering :: GIS
Requires-Python: >=3.10
License-File: LICENSE
Requires-Dist: xarray>=2022.12.0
Requires-Dist: pyproj>=3.0.0
Requires-Dist: shapely>=2.0b1
Requires-Dist: cf_xarray>=0.9.2
Requires-Dist: xproj>=0.2.0
Provides-Extra: all
Requires-Dist: xproj; extra == "all"
Requires-Dist: matplotlib; extra == "all"
Requires-Dist: geopandas; extra == "all"
Dynamic: license-file
